libmesh-0.0.6.data/scripts/meshLauncher
mesh/__init__.py
mesh/answers.py
mesh/mesh.py
mesh/utils.py
libmesh-0.0.6.dist-info/LICENSE
libmesh-0.0.6.dist-info/METADATA
libmesh-0.0.6.dist-info/WHEEL
libmesh-0.0.6.dist-info/top_level.txt
libmesh-0.0.6.dist-info/RECORD
