Metadata-Version: 2.1
Name: libmesh
Version: 0.0.6
Summary: This library can get answers from uchebnik.mos.ru 
Home-page: https://github.com/superdima05/mesh/
Author: superdima05, kinda-cookie-monster
License: GPL-3.0
Platform: UNKNOWN
Classifier: Programming Language :: Python :: 3.9
Classifier: Programming Language :: Python :: 3.10
Requires-Python: >=3.9
License-File: LICENSE
Requires-Dist: requests
